{"esti_obj.main_allperiods_obj": 7.0331968799095534, "ktp_opti_grid_allJ_agg": 13.86077846, "ib_probJ_opti_grid_j_agg": 0.107881142, "is_probJ_opti_grid_j_agg": 0.070663005, "fb2_probJ_opti_grid_j_agg": 0.209197717, "fs_probJ_opti_grid_j_agg": 0.165376048, "ibfb2_probJ_opti_grid_j_agg": 0.107522843, "fbis2_probJ_opti_grid_j_agg": 0.073679336, "none_probJ_opti_grid_j_agg": 0.265679909, "period_dictkey": "ce9901", "data_model": "model", "level_0": 24, "btp_fb_opti_grid_allJ_agg": -0.990696605, "btp_fs_opti_grid_allJ_agg": 0.001243421, "btp_ib_opti_grid_allJ_agg": -1.184485272, "btp_il_opti_grid_allJ_agg": 0.328418724, "consumption_opti_grid_allJ_agg": 4.16876425, "dist_param.data__A_mu_ce0209.params.mu": 0.620844678, "dist_param.data__A_mu_ce9901.params.mu": -0.18011238, "dist_param.data__A_sd_ce0209.params.sd": 0.531058236, "dist_param.data__A_sd_ce9901.params.sd": 0.9388918890000001, "esti_obj.main_obj": 2.7565338283416403, "esti_obj.subsets_main.agg_prob_for": 1.815727494011039, "esti_obj.subsets_main.agg_prob_inf": 0.19056906468541893, "esti_obj.subsets_main.agg_prob_jnt": 0.6521424596203544, "esti_obj.subsets_main.agg_prob_none": 0.09809481002482806, "esti_obj.subsets_main.equi_BI": 0.7328499359999999, "esti_obj.subsets_main.mean_K": 112.800257, "esti_obj.subsets_other.agg_prob": 0.342492652, "esti_obj.subsets_other.agg_prob_brr": 0.079206268, "esti_obj.subsets_other.agg_prob_sav": 0.231966293, "esti_obj.subsets_other.mean_KYC": 1.6294743430398038, "esti_obj.subsets_other.mean_fbfs": 0.0, "esti_obj.subsets_other.mean_ibil": 0.0, "esti_param.BNF_BORR_P_ce0209": 1.7531539319999998, "esti_param.BNF_BORR_P_ce9901": 0.099186085, "esti_param.BNF_SAVE_P_ce0209": 0.32527871199999997, "esti_param.BNF_SAVE_P_ce9901": 0.18466524199999998, "esti_param.BNI_BORR_P_ce0209": 2.778339102, "esti_param.BNI_BORR_P_ce9901": 0.976989368, "esti_param.BNI_LEND_P_ce0209": 3.4545132880000002, "esti_param.BNI_LEND_P_ce9901": 1.961528755, "esti_param.K_DEPRECIATION": 0.15605704, "esti_param.alpha_k": 0.595529309, "esti_param.beta": 0.9123742970000001, "esti_param.kappa_ce0209": 0.390861189, "esti_param.kappa_ce9901": 0.167263427, "esti_param.logit_sd_scale": 1.015933067, "esti_param.rho": 0.725134692, "grid_param.std_eps": 0.5511097220000001, "index": 24.0, "model_option.choice_names_use": "['ib', 'is', 'fb2', 'fs', 'ibfb2', 'fbis2', 'none']", "model_option.choice_set_list": "[0, 1, 102, 3, 104, 105, 6]", "predict": 0.0, "support_arg.param_combo_list_ctr_str": "_c624", "y_opti_grid_allJ_agg": 4.410963661}