[{"ref_type": "exactQuotation", "span": ["lat.w.Sermo59.1.9", "lat.w.Sermo59.1.15"], "target": [["Song of Songs", "2", "12"]], "source": [11, 12, 13, 14, 15, 16]}, {"ref_type": "inexactQuotation", "span": ["lat.w.Sermo59.1.24", "lat.w.Sermo59.1.30"], "target": [["John", "3", "31"]], "source": [29, 30, 31, 32, 33, 34, 35]}, {"ref_type": "inexactQuotation", "span": "lat.w.Sermo59.1.46 lat.w.Sermo59.1.47 lat.w.Sermo59.1.48 lat.w.Sermo59.1.49 lat.w.Sermo59.1.51", "target": [["Song of Songs", "2", "12"]], "source": [57, 58, 59, 60, 63]}, {"ref_type": "inexactQuotation", "span": "lat.w.Sermo59.1.55 lat.w.Sermo59.1.57 lat.w.Sermo59.1.58 lat.w.Sermo59.1.59 lat.w.Sermo59.1.60 lat.w.Sermo59.1.61 lat.w.Sermo59.1.62", "target": [["Song of Songs", "2", "12"]], "source": [69, 73, 74, 75, 76, 77, 78]}, {"ref_type": "inexactQuotation", "span": ["lat.w.Sermo59.1.94", "lat.w.Sermo59.1.96"], "target": [["Song of Songs", "2", "12"]], "source": [120, 121]}, {"ref_type": "exactQuotation", "span": ["lat.w.Sermo59.1.97", "lat.w.Sermo59.1.101"], "target": [["Psalms", "48", "3"]], "source": [124, 125, 126, 127]}, {"ref_type": "exactQuotation", "span": ["lat.w.Sermo59.1.103", "lat.w.Sermo59.1.106"], "target": [["Psalms", "125", "3"]], "source": [132, 133, 134]}, {"ref_type": "inexactQuotation", "span": "lat.w.Sermo59.1.120 lat.w.Sermo59.1.121 lat.w.Sermo59.1.123", "target": [["Song of Songs", "2", "12"]], "source": [153, 154, 158]}, {"ref_type": "inexactQuotation-allusion", "span": ["lat.w.Sermo59.1.204", "lat.w.Sermo59.1.204"], "target": [["John", "15", "15"]], "source": [261]}, {"ref_type": "exactQuotation", "span": ["lat.w.Sermo59.2.255", "lat.w.Sermo59.2.260"], "target": [["1 Corinthians", "6", "17"]], "source": [324, 325, 326, 327, 328, 329]}, {"ref_type": "inexactQuotation", "span": ["lat.w.Sermo59.2.265", "lat.w.Sermo59.2.270"], "target": [["Genesis", "3", "22"]], "source": [337, 338, 339, 340, 341]}, {"ref_type": "exactQuotation", "span": ["lat.w.Sermo59.2.308", "lat.w.Sermo59.2.311"], "target": [["Genesis", "2", "24"]], "source": [393, 394, 395]}, {"ref_type": "exactQuotation", "span": ["lat.w.Sermo59.2.308", "lat.w.Sermo59.2.311"], "target": [["Ephesians", "5", "31"]], "source": [393, 394, 395]}, {"ref_type": "exactQuotation", "span": "lat.w.Sermo59.2.320 lat.w.Sermo59.2.321 lat.w.Sermo59.2.322 lat.w.Sermo59.2.324 lat.w.Sermo59.2.325 lat.w.Sermo59.2.326 lat.w.Sermo59.2.327 lat.w.Sermo59.2.328", "target": [["Psalms", "113", "24"]], "source": [408, 409, 410, 414, 415, 416, 417, 418]}, {"ref_type": "exactQuotation", "span": ["lat.w.Sermo59.2.346", "lat.w.Sermo59.2.348"], "target": [["Song of Songs", "2", "12"]], "source": [441, 442]}, {"ref_type": "inexactQuotation", "span": ["lat.w.Sermo59.2.370", "lat.w.Sermo59.2.372"], "target": [["Song of Songs", "2", "12"]], "source": [470, 471]}, {"ref_type": "inexactQuotation", "span": ["lat.w.Sermo59.3.386", "lat.w.Sermo59.3.392"], "target": [["Song of Songs", "2", "12"]], "source": [491, 492, 493, 494, 495, 496]}, {"ref_type": "inexactQuotation", "span": "lat.w.Sermo59.3.399 lat.w.Sermo59.3.401", "target": [["Song of Songs", "2", "12"]], "source": [506, 508]}, {"ref_type": "inexactQuotation-allusion", "span": ["lat.w.Sermo59.3.463", "lat.w.Sermo59.3.463"], "target": [["Isaiah", "59", "11"]], "source": [587]}, {"ref_type": "inexactQuotation", "span": ["lat.w.Sermo59.3.485", "lat.w.Sermo59.3.489"], "target": [["Psalms", "67", "34"]], "source": [614, 615, 616, 617]}, {"ref_type": "inexactQuotation", "span": ["lat.w.Sermo59.3.527", "lat.w.Sermo59.3.543"], "target": [["Matthew", "23", "4"]], "source": [665, 666, 667, 668, 669, 670, 671, 672, 673, 674, 675, 676, 677, 678, 679, 680, 681, 682]}, {"ref_type": "inexactQuotation", "span": ["lat.w.Sermo59.3.549", "lat.w.Sermo59.3.555"], "target": [["Romans", "2", "21"]], "source": [691, 692, 693, 694, 695, 696, 697]}, {"ref_type": "exactQuotation", "span": ["lat.w.Sermo59.4.556", "lat.w.Sermo59.4.562"], "target": [["Song of Songs", "2", "12"]], "source": [700, 701, 702, 703, 704, 705]}, {"ref_type": "inexactQuotation", "span": "lat.w.Sermo59.4.574 lat.w.Sermo59.4.578 lat.w.Sermo59.4.579 lat.w.Sermo59.4.580 lat.w.Sermo59.4.581", "target": [["Deuteronomy", "6", "3"]], "source": [720, 725, 726, 727, 728]}, {"ref_type": "inexactQuotation", "span": "lat.w.Sermo59.4.585 lat.w.Sermo59.4.586 lat.w.Sermo59.4.587 lat.pc.Sermo59.4.150 lat.w.Sermo59.4.593 lat.w.Sermo59.4.594", "target": [["Hebrews", "11", "13"], ["Hebrews", "11", "14"]], "source": [733, 734, 735, 736, 742, 743]}, {"ref_type": "inexactQuotation", "span": ["lat.w.Sermo59.4.603", "lat.w.Sermo59.4.607"], "target": [["Nehemiah", "8", "10"]], "source": [754, 755, 756, 757]}, {"ref_type": "inexactQuotation", "span": ["lat.w.Sermo59.4.611", "lat.w.Sermo59.4.617"], "target": [["Song of Songs", "2", "12"]], "source": [763, 764, 765, 766, 767, 768]}, {"ref_type": "inexactQuotation", "span": ["lat.w.Sermo59.4.629", "lat.w.Sermo59.4.636"], "target": [["Hebrews", "13", "14"]], "source": [783, 784, 785, 786, 787, 788, 789, 790]}, {"ref_type": "inexactQuotation", "span": ["lat.w.Sermo59.4.668", "lat.w.Sermo59.4.670"], "target": [["Hebrews", "11", "13"]], "source": [827, 828]}, {"ref_type": "inexactQuotation", "span": ["lat.w.Sermo59.4.691", "lat.w.Sermo59.4.697"], "target": [["Song of Songs", "2", "12"]], "source": [853, 854, 855, 856, 857, 858]}, {"ref_type": "exactQuotation", "span": ["lat.w.Sermo59.4.708", "lat.w.Sermo59.4.721"], "target": [["Psalms", "37", "10"]], "source": [872, 873, 874, 875, 876, 877, 878, 879, 880, 881, 882, 883, 884, 885, 886]}, {"ref_type": "inexactQuotation", "span": "lat.w.Sermo59.4.722 lat.w.Sermo59.4.723 lat.w.Sermo59.4.724 lat.w.Sermo59.4.725 lat.pc.Sermo59.4.169 lat.w.Sermo59.4.733 lat.w.Sermo59.4.734 lat.w.Sermo59.4.735 lat.w.Sermo59.4.736 lat.w.Sermo59.4.737 lat.w.Sermo59.4.738 lat.pc.Sermo59.4.172 lat.w.Sermo59.4.739 lat.w.Sermo59.4.740 lat.w.Sermo59.4.741 lat.w.Sermo59.4.742 lat.w.Sermo59.4.743", "target": [["Psalms", "6", "7"]], "source": [889, 890, 891, 892, 893, 903, 904, 905, 906, 907, 908, 909, 910, 911, 912, 913, 914]}, {"ref_type": "inexactQuotation", "span": ["lat.w.Sermo59.4.744", "lat.w.Sermo59.4.754"], "target": [["2 Timothy", "4", "8"]], "source": [916, 917, 918, 919, 920, 921, 922, 923, 924, 925, 926]}, {"ref_type": "inexactQuotation", "span": "lat.w.Sermo59.4.765 lat.w.Sermo59.4.766 lat.w.Sermo59.4.768 lat.w.Sermo59.4.769 lat.w.Sermo59.4.770 lat.pc.Sermo59.4.180 lat.w.Sermo59.4.771 lat.w.Sermo59.4.772 lat.w.Sermo59.4.773 lat.w.Sermo59.4.774 lat.w.Sermo59.4.775 lat.pc.Sermo59.4.181 lat.w.Sermo59.4.776 lat.w.Sermo59.4.777 lat.w.Sermo59.4.778 lat.pc.Sermo59.4.182 lat.w.Sermo59.4.779 lat.w.Sermo59.4.780 lat.w.Sermo59.4.781 lat.w.Sermo59.4.782 lat.w.Sermo59.4.783 lat.pc.Sermo59.4.183 lat.w.Sermo59.4.784 lat.w.Sermo59.4.785 lat.w.Sermo59.4.786", "target": [["Matthew", "9", "15"]], "source": [941, 942, 946, 947, 948, 949, 950, 951, 952, 953, 954, 955, 956, 957, 958, 959, 960, 961, 962, 963, 964, 965, 966, 967, 968]}, {"ref_type": "inexactQuotation", "span": ["lat.w.Sermo59.5.802", "lat.w.Sermo59.5.830"], "target": [["Romans", "8", "19"], ["Romans", "8", "21"], ["Romans", "8", "22"]], "source": [990, 991, 992, 993, 994, 995, 996, 997, 998, 999, 1000, 1001, 1002, 1003, 1004, 1005, 1006, 1007, 1008, 1009, 1010, 1011, 1012, 1013, 1014, 1015, 1016, 1017, 1018, 1019, 1020, 1021, 1022]}, {"ref_type": "inexactQuotation", "span": "lat.w.Sermo59.5.834 lat.w.Sermo59.5.835 lat.w.Sermo59.5.836 lat.w.Sermo59.5.837 lat.pc.Sermo59.5.197 lat.w.Sermo59.5.839 lat.w.Sermo59.5.840", "target": [["2 Corinthians", "5", "6"]], "source": [1029, 1030, 1031, 1032, 1034, 1035, 1036]}, {"ref_type": "exactQuotation", "span": ["lat.w.Sermo59.5.851", "lat.w.Sermo59.5.860"], "target": [["Psalms", "11", "6"]], "source": [1050, 1051, 1052, 1053, 1054, 1055, 1056, 1057, 1058, 1059, 1060]}, {"ref_type": "exactQuotation", "span": ["lat.w.Sermo59.5.880", "lat.w.Sermo59.5.885"], "target": [["Isaiah", "24", "16"]], "source": [1086, 1087, 1088, 1089, 1090, 1091]}, {"ref_type": "exactQuotation", "span": ["lat.w.Sermo59.5.890", "lat.w.Sermo59.5.896"], "target": [["Psalms", "37", "10"]], "source": [1099, 1100, 1101, 1102, 1103, 1104]}, {"ref_type": "exactQuotation", "span": ["lat.w.Sermo59.5.913", "lat.w.Sermo59.5.919"], "target": [["Song of Songs", "2", "12"]], "source": [1126, 1127, 1128, 1129, 1130, 1131]}, {"ref_type": "exactQuotation", "span": ["lat.w.Sermo59.5.935", "lat.w.Sermo59.5.945"], "target": [["Colossians", "3", "1"]], "source": [1151, 1152, 1153, 1154, 1155, 1156, 1157, 1158, 1159, 1160, 1161]}, {"ref_type": "inexactQuotation", "span": ["lat.w.Sermo59.5.969", "lat.w.Sermo59.5.979"], "target": [["Jeremiah", "31", "34"]], "source": [1190, 1191, 1192, 1193, 1194, 1195, 1196, 1197, 1198, 1199, 1200]}, {"ref_type": "exactQuotation", "span": ["lat.w.Sermo59.6.999", "lat.w.Sermo59.6.1000"], "target": [["Song of Songs", "2", "12"]], "source": [1227]}, {"ref_type": "inexactQuotation", "span": ["lat.w.Sermo59.6.1014", "lat.w.Sermo59.6.1020"], "target": [["Romans", "8", "26"]], "source": [1246, 1247, 1248, 1249, 1250, 1251, 1252]}, {"ref_type": "exactQuotation", "span": ["lat.w.Sermo59.6.1055", "lat.w.Sermo59.6.1060"], "target": [["1 Corinthians", "12", "7"]], "source": [1297, 1298, 1299, 1300, 1301]}, {"ref_type": "inexactQuotation", "span": "lat.w.Sermo59.6.1078 lat.w.Sermo59.6.1080 lat.w.Sermo59.6.1081 lat.w.Sermo59.6.1082 lat.pc.Sermo59.6.251 lat.w.Sermo59.6.1083 lat.w.Sermo59.6.1084 lat.w.Sermo59.6.1085 lat.w.Sermo59.6.1086 lat.pc.Sermo59.6.252 lat.w.Sermo59.6.1087 lat.w.Sermo59.6.1088 lat.w.Sermo59.6.1089 lat.w.Sermo59.6.1090 lat.w.Sermo59.6.1091 lat.w.Sermo59.6.1092 lat.w.Sermo59.6.1093", "target": [["John", "3", "8"]], "source": [1325, 1329, 1330, 1331, 1332, 1333, 1334, 1335, 1336, 1337, 1338, 1339, 1340, 1341, 1342, 1343, 1344]}, {"ref_type": "inexactQuotation", "span": ["lat.w.Sermo59.6.1098", "lat.w.Sermo59.6.1099"], "target": [["2 Corinthians", "3", "6"]], "source": [1351]}, {"ref_type": "inexactQuotation", "span": ["lat.w.Sermo59.6.1107", "lat.w.Sermo59.6.1111"], "target": [["1 John", "3", "14"]], "source": [1362, 1363, 1364, 1365]}, {"ref_type": "inexactQuotation", "span": ["lat.w.Sermo59.6.1113", "lat.w.Sermo59.6.1114"], "target": [["1 Corinthians", "15", "45"]], "source": [1368]}, {"ref_type": "inexactQuotation", "span": ["lat.w.Sermo59.6.1135", "lat.w.Sermo59.6.1139"], "target": [["Genesis", "33", "10"]], "source": [1395, 1396, 1397, 1398]}, {"ref_type": "inexactQuotation", "span": ["lat.w.Sermo59.6.1135", "lat.w.Sermo59.6.1139"], "target": [["Judith", "10", "12"]], "source": [1395, 1396, 1397, 1398]}, {"ref_type": "inexactQuotation", "span": ["lat.w.Sermo59.6.1149", "lat.w.Sermo59.6.1159"], "target": [["Romans", "8", "26"]], "source": [1411, 1412, 1413, 1414, 1415, 1416, 1417, 1418, 1419, 1420, 1421]}, {"ref_type": "exactQuotation", "span": ["lat.w.Sermo59.7.1181", "lat.w.Sermo59.7.1186"], "target": [["Luke", "2", "24"]], "source": [1449, 1450, 1451, 1452, 1453]}, {"ref_type": "exactQuotation", "span": ["lat.w.Sermo59.8.1356", "lat.w.Sermo59.8.1361"], "target": [["Genesis", "1", "28"]], "source": [1654, 1655, 1656, 1657, 1658, 1659]}, {"ref_type": "exactQuotation", "span": ["lat.w.Sermo59.8.1356", "lat.w.Sermo59.8.1361"], "target": [["Genesis", "9", "1"]], "source": [1654, 1655, 1656, 1657, 1658, 1659]}, {"ref_type": "exactQuotation", "span": ["lat.w.Sermo59.8.1377", "lat.w.Sermo59.8.1386"], "target": [["Mark", "12", "25"]], "source": [1679, 1680, 1681, 1682, 1683, 1684, 1685, 1686, 1687, 1688, 1689]}, {"ref_type": "inexactQuotation-allusion", "span": ["lat.w.Sermo59.8.1377", "lat.w.Sermo59.8.1386"], "target": [["Luke", "20", "35"]], "source": [1679, 1680, 1681, 1682, 1683, 1684, 1685, 1686, 1687, 1688, 1689]}, {"ref_type": "inexactQuotation", "span": ["lat.w.Sermo59.8.1409", "lat.w.Sermo59.8.1415"], "target": [["Deuteronomy", "25", "5"]], "source": [1717, 1718, 1719, 1720, 1721, 1722]}, {"ref_type": "inexactQuotation", "span": "lat.w.Sermo59.8.1429 lat.w.Sermo59.8.1430 lat.w.Sermo59.8.1431 lat.w.Sermo59.8.1432 lat.w.Sermo59.8.1433", "target": [["Matthew", "19", "12"]], "source": [1739, 1740, 1741, 1742, 1743]}, {"ref_type": "inexactQuotation", "span": ["lat.w.Sermo59.8.1441", "lat.w.Sermo59.8.1443"], "target": [["1 Corinthians", "7", "25"]], "source": [1752, 1753]}, {"ref_type": "exactQuotation", "span": ["lat.w.Sermo59.8.1452", "lat.w.Sermo59.8.1458"], "target": [["Song of Songs", "2", "12"]], "source": [1765, 1766, 1767, 1768, 1769, 1770]}, {"ref_type": "inexactQuotation", "span": "lat.w.Sermo59.9.1472 lat.w.Sermo59.9.1473 lat.w.Sermo59.9.1474 lat.w.Sermo59.9.1476 lat.w.Sermo59.9.1477 lat.pc.Sermo59.9.320 lat.w.Sermo59.9.1479 lat.w.Sermo59.9.1480 lat.w.Sermo59.9.1481 lat.w.Sermo59.9.1482", "target": [["Song of Songs", "2", "12"]], "source": [1790, 1791, 1792, 1794, 1795, 1796, 1798, 1799, 1800, 1801]}, {"ref_type": "exactQuotation", "span": ["lat.w.Sermo59.9.1511", "lat.w.Sermo59.9.1513"], "target": [["Romans", "10", "17"]], "source": [1840, 1841]}, {"ref_type": "exactQuotation", "span": ["lat.w.Sermo59.9.1524", "lat.w.Sermo59.9.1528"], "target": [["Psalms", "84", "12"]], "source": [1857, 1858, 1859, 1860]}, {"ref_type": "inexactQuotation", "span": ["lat.w.Sermo59.9.1537", "lat.w.Sermo59.9.1538"], "target": [["Hebrews", "11", "39"]], "source": [1871]}, {"ref_type": "inexactQuotation", "span": "lat.w.Sermo59.9.1539 lat.w.Sermo59.9.1541 lat.w.Sermo59.9.1542 lat.w.Sermo59.9.1543 lat.w.Sermo59.9.1544", "target": [["Psalms", "92", "5"]], "source": [1874, 1876, 1877, 1878, 1879]}, {"ref_type": "inexactQuotation-allusion", "span": ["lat.w.Sermo59.9.1556", "lat.w.Sermo59.9.1556"], "target": [["Matthew", "18", "16"]], "source": [1895]}, {"ref_type": "inexactQuotation", "span": "lat.w.Sermo59.9.1568 lat.pc.Sermo59.9.343 lat.w.Sermo59.9.1569 lat.w.Sermo59.9.1570 lat.w.Sermo59.9.1577 lat.w.Sermo59.9.1578 lat.w.Sermo59.9.1579 lat.w.Sermo59.9.1580", "target": [["Luke", "7", "22"]], "source": [1909, 1910, 1911, 1912, 1919, 1920, 1921, 1922]}, {"ref_type": "inexactQuotation", "span": "lat.w.Sermo59.9.1568 lat.pc.Sermo59.9.343 lat.w.Sermo59.9.1569 lat.w.Sermo59.9.1570 lat.w.Sermo59.9.1577 lat.w.Sermo59.9.1578 lat.w.Sermo59.9.1579 lat.w.Sermo59.9.1580", "target": [["Matthew", "11", "4"]], "source": [1909, 1910, 1911, 1912, 1919, 1920, 1921, 1922]}, {"ref_type": "exactQuotation", "span": ["lat.w.Sermo59.9.1610", "lat.w.Sermo59.9.1611"], "target": [["Romans", "9", "28"]], "source": [1960]}, {"ref_type": "inexactQuotation", "span": ["lat.w.Sermo59.9.1613", "lat.w.Sermo59.9.1615"], "target": [["Hebrews", "4", "12"]], "source": [1964, 1965]}, {"ref_type": "inexactQuotation", "span": "lat.w.Sermo59.9.1643 lat.w.Sermo59.9.1645 lat.w.Sermo59.9.1646 lat.pc.Sermo59.9.362 lat.w.Sermo59.9.1647 lat.w.Sermo59.9.1648 lat.w.Sermo59.9.1649 lat.w.Sermo59.9.1650 lat.w.Sermo59.9.1651 lat.pc.Sermo59.9.363 lat.w.Sermo59.9.1652 lat.w.Sermo59.9.1653", "target": [["Mark", "16", "20"]], "source": [2003, 2005, 2006, 2007, 2008, 2009, 2010, 2011, 2012, 2013, 2014, 2015]}, {"ref_type": "inexactQuotation-allusion", "span": ["lat.w.Sermo59.9.1664", "lat.w.Sermo59.9.1664"], "target": [["Matthew", "17", "2"], ["Matthew", "17", "5"]], "source": [2028]}, {"ref_type": "inexactQuotation-allusion", "span": ["lat.w.Sermo59.9.1674", "lat.w.Sermo59.9.1674"], "target": [["Matthew", "3", "13"], ["Matthew", "3", "16"]], "source": [2040]}, {"ref_type": "exactQuotation", "span": ["lat.w.Sermo59.10.1701", "lat.w.Sermo59.10.1704"], "target": [["Song of Songs", "2", "13"]], "source": [2073, 2074, 2075]}, {"ref_type": "inexactQuotation-allusion", "span": ["lat.w.Sermo59.10.1708", "lat.w.Sermo59.10.1708"], "target": [["Genesis", "3", "3"]], "source": [2081]}, {"ref_type": "exactQuotation", "span": ["lat.w.Sermo59.10.1746", "lat.w.Sermo59.10.1751"], "target": [["Psalms", "128", "6"]], "source": [2128, 2129, 2130, 2131, 2132, 2133, 2134, 2135]}, {"ref_type": "inexactQuotation", "span": ["lat.w.Sermo59.10.1833", "lat.w.Sermo59.10.1835"], "target": [["Philippians", "1", "11"]], "source": [2233, 2234]}, {"ref_type": "exactQuotation", "span": ["lat.w.Sermo59.10.1842", "lat.w.Sermo59.10.1850"], "target": [["Romans", "9", "5"]], "source": [2244, 2245, 2246, 2247, 2248, 2249, 2250, 2251, 2252]}]